pycalista_ista/__init__.py
pycalista_ista/__version.py
pycalista_ista/const.py
pycalista_ista/excel_parser.py
pycalista_ista/exception_classes.py
pycalista_ista/pycalista_ista.py
pycalista_ista/virtual_api.py
pycalista_ista/models/__init__.py
pycalista_ista/models/cold_water_device.py
pycalista_ista/models/device.py
pycalista_ista/models/heating_device.py
pycalista_ista/models/hot_water_device.py
pycalista_ista/models/reading.py
pycalista_ista/models/water_device.py
pycalista_ista-0.6.0.dist-info/licenses/LICENSE
pycalista_ista-0.6.0.dist-info/METADATA
pycalista_ista-0.6.0.dist-info/WHEEL
pycalista_ista-0.6.0.dist-info/top_level.txt
pycalista_ista-0.6.0.dist-info/RECORD
