Metadata-Version: 2.4
Name: pycalista-ista
Version: 0.6.0
Summary: Python library for the ista calista service
Home-page: https://github.com/herruzo99/pycalista-ista
Author: Juan Herruzo
Author-email: Juan Herruzo <juan@herruzo.dev>
License: MIT
Project-URL: Homepage, https://github.com/herruzo99/pycalista-ista
Project-URL: Documentation, https://github.com/herruzo99/pycalista-ista#readme
Project-URL: Repository, https://github.com/herruzo99/pycalista-ista.git
Project-URL: Issues, https://github.com/herruzo99/pycalista-ista/issues
Classifier: Development Status :: 3 - Alpha
Classifier: Intended Audience :: Developers
Classifier: License :: OSI Approved :: MIT License
Classifier: Operating System :: OS Independent
Classifier: Programming Language :: Python :: 3
Classifier: Programming Language :: Python :: 3.12
Classifier: Topic :: Software Development :: Libraries :: Python Modules
Requires-Python: >=3.12
License-File: LICENSE
Requires-Dist: requests>=2.31.0
Requires-Dist: pandas>=2.2.0
Requires-Dist: xlrd>=2.0.1
Requires-Dist: unidecode>=1.3.8
Requires-Dist: aiohttp>=3.11.16
Requires-Dist: yarl>=1.19.0
Provides-Extra: dev
Requires-Dist: aioresponses; extra == "dev"
Requires-Dist: pytest; extra == "dev"
Requires-Dist: pytest-cov; extra == "dev"
Requires-Dist: pytest-asyncio; extra == "dev"
Requires-Dist: requests-mock; extra == "dev"
Requires-Dist: black; extra == "dev"
Requires-Dist: isort; extra == "dev"
Requires-Dist: xlwt; extra == "dev"
Requires-Dist: ruff; extra == "dev"
Requires-Dist: pre-commit; extra == "dev"
Dynamic: author
Dynamic: home-page
Dynamic: license-file
Dynamic: requires-python
